{
  "meta": {
    "success": true,
    "message": "ok"
  },
  "data": [
    {
      "hour": "0",
      "date": "2017/11/05",
      "hourFormat": "00:00",
      "channelExp": "",
      "activityExp": "",
      "versionsExp": "5.08",
      "contentExp": ""
    },
    {
      "hour": "1",
      "date": "2017/11/05",
      "hourFormat": "01:00",
      "channelExp": "",
      "activityExp": "",
      "versionsExp": "18.88",
      "contentExp": ""
    },
    {
      "hour": "2",
      "date": "2017/11/05",
      "hourFormat": "02:00",
      "channelExp": "",
      "activityExp": "",
      "versionsExp": "21.65",
      "contentExp": ""
    },
    {
      "hour": "3",
      "date": "2017/11/05",
      "hourFormat": "03:00",
      "channelExp": "",
      "activityExp": "",
      "versionsExp": "11.15",
      "contentExp": ""
    },
    {
      "hour": "4",
      "date": "2017/11/05",
      "hourFormat": "04:00",
      "channelExp": "",
      "activityExp": "",
      "versionsExp": "19.75",
      "contentExp": ""
    },
    {
      "hour": "5",
      "date": "2017/11/05",
      "hourFormat": "05:00",
      "channelExp": "",
      "activityExp": "",
      "versionsExp": "22.90",
      "contentExp": ""
    },
    {
      "hour": "6",
      "date": "2017/11/05",
      "hourFormat": "06:00",
      "channelExp": "",
      "activityExp": "",
      "versionsExp": "14.50",
      "contentExp": ""
    },
    {
      "hour": "7",
      "date": "2017/11/05",
      "hourFormat": "07:00",
      "channelExp": "",
      "activityExp": "",
      "versionsExp": "3.56",
      "contentExp": ""
    },
    {
      "hour": "8",
      "date": "2017/11/05",
      "hourFormat": "08:00",
      "channelExp": "",
      "activityExp": "",
      "versionsExp": "3.04",
      "contentExp": ""
    },
    {
      "hour": "9",
      "date": "2017/11/05",
      "hourFormat": "09:00",
      "channelExp": "",
      "activityExp": "",
      "versionsExp": "4.68",
      "contentExp": ""
    },
    {
      "hour": "10",
      "date": "2017/11/05",
      "hourFormat": "10:00",
      "channelExp": "",
      "activityExp": "",
      "versionsExp": "5.71",
      "contentExp": ""
    },
    {
      "hour": "11",
      "date": "2017/11/05",
      "hourFormat": "11:00",
      "channelExp": "",
      "activityExp": "",
      "versionsExp": "17.00",
      "contentExp": ""
    },
    {
      "hour": "12",
      "date": "2017/11/05",
      "hourFormat": "12:00",
      "channelExp": "",
      "activityExp": "",
      "versionsExp": "8.24",
      "contentExp": ""
    },
    {
      "hour": "13",
      "date": "2017/11/05",
      "hourFormat": "13:00",
      "channelExp": "",
      "activityExp": "",
      "versionsExp": "14.23",
      "contentExp": ""
    },
    {
      "hour": "14",
      "date": "2017/11/05",
      "hourFormat": "14:00",
      "channelExp": "",
      "activityExp": "",
      "versionsExp": "3.94",
      "contentExp": ""
    },
    {
      "hour": "15",
      "date": "2017/11/05",
      "hourFormat": "15:00",
      "channelExp": "",
      "activityExp": "",
      "versionsExp": "18.59",
      "contentExp": ""
    },
    {
      "hour": "16",
      "date": "2017/11/05",
      "hourFormat": "16:00",
      "channelExp": "",
      "activityExp": "",
      "versionsExp": "7.72",
      "contentExp": ""
    },
    {
      "hour": "17",
      "date": "2017/11/05",
      "hourFormat": "17:00",
      "channelExp": "",
      "activityExp": "",
      "versionsExp": "8.91",
      "contentExp": ""
    },
    {
      "hour": "18",
      "date": "2017/11/05",
      "hourFormat": "18:00",
      "channelExp": "",
      "activityExp": "",
      "versionsExp": "3.80",
      "contentExp": ""
    },
    {
      "hour": "19",
      "date": "2017/11/05",
      "hourFormat": "19:00",
      "channelExp": "",
      "activityExp": "",
      "versionsExp": "12.46",
      "contentExp": ""
    },
    {
      "hour": "20",
      "date": "2017/11/05",
      "hourFormat": "20:00",
      "channelExp": "",
      "activityExp": "",
      "versionsExp": "3.22",
      "contentExp": ""
    },
    {
      "hour": "21",
      "date": "2017/11/05",
      "hourFormat": "21:00",
      "channelExp": "",
      "activityExp": "",
      "versionsExp": "3.94",
      "contentExp": ""
    },
    {
      "hour": "22",
      "date": "2017/11/05",
      "hourFormat": "22:00",
      "channelExp": "",
      "activityExp": "",
      "versionsExp": "2.85",
      "contentExp": ""
    },
    {
      "hour": "23",
      "date": "2017/11/05",
      "hourFormat": "23:00",
      "channelExp": "",
      "activityExp": "",
      "versionsExp": "4.00",
      "contentExp": ""
    }
  ]
}